pyadcirc/__init__.py
pyadcirc/cli.py
pyadcirc/utils.py
pyadcirc/configs/__init__.py
pyadcirc/configs/adcirc_configs.json
pyadcirc/configs/noaa_stations.json
pyadcirc/data/cli.py
pyadcirc/data/ncar.py
pyadcirc/data/noaa.py
pyadcirc/data/utils.py
pyadcirc/io/io.py
pyadcirc/io/io_cli.py
pyadcirc/scripts/adcirc_compile.sh
pyadcirc/scripts/git_setup.sh
pyadcirc/scripts/pull_adcirc_param_configs.py
pyadcirc/scripts/scripts.py
pyadcirc/scripts/sys_command.sh
pyadcirc/sim/generators.py
pyadcirc/sim/sim_cli.py
pyadcirc/sim/tacc.py
pyadcirc/sim/hpc_apps/adcirc/assets/run.sh
pyadcirc/sim/hpc_apps/adcirc/assets/.ipynb_checkpoints/run-checkpoint.sh
pyadcirc/sim/hpc_apps/adcirc/configs/taccjm/app.json
pyadcirc/sim/hpc_apps/adcirc/configs/taccjm/frontera.ini
pyadcirc/sim/hpc_apps/adcirc/configs/taccjm/job.json
pyadcirc/sim/hpc_apps/adcirc/configs/taccjm/ls6.ini
pyadcirc/sim/hpc_apps/adcirc/configs/taccjm/stampede2.ini
pyadcirc/sim/hpc_apps/adcirc/configs/tapis/app.json
pyadcirc/sim/hpc_apps/adcirc/configs/tapis/frontera.ini
pyadcirc/sim/hpc_apps/adcirc/configs/tapis/job.json
pyadcirc/sim/hpc_apps/adcirc/configs/tapis/ls6.ini
pyadcirc/sim/hpc_apps/adcirc/configs/tapis/stampede2.ini
pyadcirc/sim/hpc_apps/pylauncher/assets/pylauncher4.py
pyadcirc/sim/hpc_apps/pylauncher/assets/run.sh
pyadcirc/sim/hpc_apps/pylauncher/assets/test.sh
pyadcirc/sim/hpc_apps/pylauncher/configs/taccjm/app.json
pyadcirc/sim/hpc_apps/pylauncher/configs/taccjm/frontera.ini
pyadcirc/sim/hpc_apps/pylauncher/configs/taccjm/job.json
pyadcirc/sim/hpc_apps/pylauncher/configs/taccjm/ls6.ini
pyadcirc/sim/hpc_apps/pylauncher/configs/taccjm/project.ini
pyadcirc/sim/hpc_apps/pylauncher/configs/taccjm/stampede2.ini
pyadcirc/sim/hpc_apps/pylauncher/configs/tapis/app.json
pyadcirc/sim/hpc_apps/pylauncher/configs/tapis/project.ini
pyadcirc/sim/hpc_apps/pylauncher/configs/tapis/stampede2.json
pyadcirc/sim/hpc_apps/pylauncher/configs/tapis/tapis-stampede2.ini
pyadcirc/sim/hpc_apps/pylauncher/inputs/adcirc.zip
pyadcirc-0.0.1.dist-info/AUTHORS.rst
pyadcirc-0.0.1.dist-info/LICENSE.txt
pyadcirc-0.0.1.dist-info/METADATA
pyadcirc-0.0.1.dist-info/WHEEL
pyadcirc-0.0.1.dist-info/entry_points.txt
pyadcirc-0.0.1.dist-info/top_level.txt
pyadcirc-0.0.1.dist-info/RECORD
